SciProgPackage/ScientificProgramming.py
SciProgPackage/__init__.py
SciProgPackage-1.2.0.dist-info/METADATA
SciProgPackage-1.2.0.dist-info/WHEEL
SciProgPackage-1.2.0.dist-info/top_level.txt
SciProgPackage-1.2.0.dist-info/RECORD
